cavro.cp312-win_amd64.pyd
cavro-1.0.0.dist-info/LICENSE
cavro-1.0.0.dist-info/METADATA
cavro-1.0.0.dist-info/WHEEL
cavro-1.0.0.dist-info/top_level.txt
cavro-1.0.0.dist-info/RECORD
